LICENSE
MANIFEST.in
README.rst
setup.py
django_organice_theme_rssk.egg-info/PKG-INFO
django_organice_theme_rssk.egg-info/SOURCES.txt
django_organice_theme_rssk.egg-info/dependency_links.txt
django_organice_theme_rssk.egg-info/not-zip-safe
django_organice_theme_rssk.egg-info/requires.txt
django_organice_theme_rssk.egg-info/top_level.txt
organice_theme_rssk/__init__.py
organice_theme_rssk/static/favicon.ico
organice_theme_rssk/static/logo.png
organice_theme_rssk/static/css/styles.css
organice_theme_rssk/static/img/header-signet.png
organice_theme_rssk/static/img/buttons/siegel-seit1980.png
organice_theme_rssk/static/img/header/headerbilder-test.jpg
organice_theme_rssk/static/js/scripts.js
organice_theme_rssk/templates/base.html
organice_theme_rssk/templates/cms_welcome.html
organice_theme_rssk/templates/skeleton.html
organice_theme_rssk/templatetags/__init__.py
organice_theme_rssk/templatetags/rsskmedia.py